netzeus_core_schemas/__init__.py
netzeus_core_schemas/access_token.py
netzeus_core_schemas/api_key.py
netzeus_core_schemas/device.py
netzeus_core_schemas/enums.py
netzeus_core_schemas/network_driver.py
netzeus_core_schemas/user.py
netzeus_core_schemas-0.0.1.dist-info/METADATA
netzeus_core_schemas-0.0.1.dist-info/WHEEL
netzeus_core_schemas-0.0.1.dist-info/top_level.txt
netzeus_core_schemas-0.0.1.dist-info/RECORD
