Metadata-Version: 2.1
Name: netzeus-core-schemas
Version: 0.0.1
Summary: NetZeus Core Schemas module for managing shared pydantic schemas across all microservices/plugins
Author: Brandon Spendlove
Author-email: brandon.spendlove@netzeus.io
Requires-Dist: pydantic (>=1.10.2)
